{
    "": [
        "readme.md", 
        "asset", 
        "media"
    ], 
    "__raw_positions": {
        "media/14550703199125": 14, 
        "media/14486029516788": 3, 
        "media/14553496556586": 18, 
        "media/14548332725837": 15, 
        "asset/js/vendor": 2, 
        "media/14524239808681": 23, 
        "media/14544071880450": 17, 
        "media/14523378366621": 20, 
        "asset/img/social": 1, 
        "media": 3, 
        "media/14553325891591": 11, 
        "asset/highlightjs": 5, 
        "media/14584798852962": 5, 
        "asset": 2, 
        "media/14477677420859": 2, 
        "media/14572293989748": 10, 
        "media/14544127392119": 13, 
        "media/14527795875733": 4, 
        "media/14534699695139": 7, 
        "media/14532974262719": 19, 
        "media/14528325658914": 9, 
        "asset/css": 4, 
        "media/14554505293740": 22, 
        "asset/robots.txt": 2, 
        "media/14618443181690": 6, 
        "media/14542542461155": 12, 
        "asset/js/foundation": 1, 
        "media/14487770082898": 1, 
        "asset/chart": 3, 
        "readme.md": 1, 
        "asset/img": 6, 
        "media/14505840679538": 8, 
        "asset/humans.txt": 1, 
        "media/14532972201517": 21, 
        "media/14542959767841": 16, 
        "asset/js": 7
    }, 
    "media": [
        "14487770082898", 
        "14477677420859", 
        "14486029516788", 
        "14527795875733", 
        "14584798852962", 
        "14618443181690", 
        "14534699695139", 
        "14505840679538", 
        "14528325658914", 
        "14572293989748", 
        "14553325891591", 
        "14542542461155", 
        "14544127392119", 
        "14550703199125", 
        "14548332725837", 
        "14542959767841", 
        "14544071880450", 
        "14553496556586", 
        "14532974262719", 
        "14523378366621", 
        "14532972201517", 
        "14554505293740", 
        "14524239808681"
    ], 
    "asset": [
        "humans.txt", 
        "robots.txt", 
        "chart", 
        "css", 
        "highlightjs", 
        "img", 
        "js"
    ], 
    "__positions": {
        "media/14550703199125": 3014, 
        "media/14486029516788": 3003, 
        "media/14553496556586": 3018, 
        "media/14548332725837": 3015, 
        "asset/chart": 2003, 
        "asset/js/vendor": 2007002, 
        "media/14544071880450": 3017, 
        "media/14553325891591": 3011, 
        "asset/img/social": 2006001, 
        "media": 3, 
        "media/14523378366621": 3020, 
        "asset/img": 2006, 
        "media/14584798852962": 3005, 
        "media/14532974262719": 3019, 
        "media/14477677420859": 3002, 
        "media/14572293989748": 3010, 
        "media/14544127392119": 3013, 
        "media/14527795875733": 3004, 
        "media/14534699695139": 3007, 
        "asset": 2, 
        "media/14524239808681": 3023, 
        "asset/css": 2004, 
        "media/14554505293740": 3022, 
        "media/14528325658914": 3009, 
        "asset/robots.txt": 2002, 
        "media/14618443181690": 3006, 
        "media/14542542461155": 3012, 
        "asset/js/foundation": 2007001, 
        "media/14487770082898": 3001, 
        "asset/highlightjs": 2005, 
        "readme.md": 1, 
        "media/14505840679538": 3008, 
        "asset/humans.txt": 2001, 
        "media/14532972201517": 3021, 
        "media/14542959767841": 3016, 
        "asset/js": 2007
    }, 
    "asset/img": [
        "social"
    ], 
    "asset/js": [
        "foundation", 
        "vendor"
    ]
}